Metadata-Version: 2.1
Name: compositional
Version: 2022.8.31
Summary: Compositional data analysis in Python
Home-page: https://github.com/jolespin/compositional
Author: Josh L. Espinoza
Author-email: jespinoz@jcvi.org
License: BSD-3
License-File: LICENSE.txt
